CHANGELOG.txt
LICENCE.txt
MANIFEST.in
README.txt
setup.py
distributions/Binomialdistribution.py
distributions/Gaussiandistribution.py
distributions/Generaldistribution.py
distributions/__init__.py
distributions26051995.egg-info/PKG-INFO
distributions26051995.egg-info/SOURCES.txt
distributions26051995.egg-info/dependency_links.txt
distributions26051995.egg-info/not-zip-safe
distributions26051995.egg-info/top_level.txt
venv_test/Lib/site-packages/_distutils_hack/__init__.py
venv_test/Lib/site-packages/_distutils_hack/override.py
venv_test/Lib/site-packages/pip/__init__.py
venv_test/Lib/site-packages/pip/__main__.py
venv_test/Lib/site-packages/pip-21.2.4.dist-info/LICENSE.txt
venv_test/Lib/site-packages/pip-21.2.4.dist-info/entry_points.txt
venv_test/Lib/site-packages/pip-21.2.4.dist-info/top_level.txt
venv_test/Lib/site-packages/pip/_internal/__init__.py
venv_test/Lib/site-packages/pip/_internal/build_env.py
venv_test/Lib/site-packages/pip/_internal/cache.py
venv_test/Lib/site-packages/pip/_internal/configuration.py
venv_test/Lib/site-packages/pip/_internal/exceptions.py
venv_test/Lib/site-packages/pip/_internal/main.py
venv_test/Lib/site-packages/pip/_internal/pyproject.py
venv_test/Lib/site-packages/pip/_internal/self_outdated_check.py
venv_test/Lib/site-packages/pip/_internal/wheel_builder.py
venv_test/Lib/site-packages/pip/_internal/cli/__init__.py
venv_test/Lib/site-packages/pip/_internal/cli/autocompletion.py
venv_test/Lib/site-packages/pip/_internal/cli/base_command.py
venv_test/Lib/site-packages/pip/_internal/cli/cmdoptions.py
venv_test/Lib/site-packages/pip/_internal/cli/command_context.py
venv_test/Lib/site-packages/pip/_internal/cli/main.py
venv_test/Lib/site-packages/pip/_internal/cli/main_parser.py
venv_test/Lib/site-packages/pip/_internal/cli/parser.py
venv_test/Lib/site-packages/pip/_internal/cli/progress_bars.py
venv_test/Lib/site-packages/pip/_internal/cli/req_command.py
venv_test/Lib/site-packages/pip/_internal/cli/spinners.py
venv_test/Lib/site-packages/pip/_internal/cli/status_codes.py
venv_test/Lib/site-packages/pip/_internal/commands/__init__.py
venv_test/Lib/site-packages/pip/_internal/commands/cache.py
venv_test/Lib/site-packages/pip/_internal/commands/check.py
venv_test/Lib/site-packages/pip/_internal/commands/completion.py
venv_test/Lib/site-packages/pip/_internal/commands/configuration.py
venv_test/Lib/site-packages/setuptools-58.1.0.dist-info/entry_points.txt
venv_test/Lib/site-packages/setuptools-58.1.0.dist-info/top_level.txt
