Metadata-Version: 2.1
Name: distributions26051995
Version: 0.1
Summary: Gaussian distributions
Home-page: UNKNOWN
Author: Davi Misturini
Author-email: misturinidavi@gmail.com
License: MIT
Platform: UNKNOWN
License-File: LICENCE.txt
